pyprismic/__init__.py
pyprismic/exceptions.py
pyprismic/util.py
pyprismic-0.2.1.dist-info/WHEEL
pyprismic-0.2.1.dist-info/METADATA
pyprismic-0.2.1.dist-info/RECORD
