Metadata-Version: 2.1
Name: pyprismic
Version: 0.2.1
Summary: A simple Prismic client
License: LGPL-3.0-or-later
Author: Daniel Lombraña González
Author-email: daniel.lombrana@b4motion.com
Requires-Python: >=3.8,<4.0
Classifier: License :: OSI Approved :: GNU Lesser General Public License v3 or later (LGPLv3+)
Classifier: Programming Language :: Python :: 3
Classifier: Programming Language :: Python :: 3.8
Classifier: Programming Language :: Python :: 3.9
Requires-Dist: requests (>=2.27.1,<3.0.0)
